{
  "tag": "",
  "generation": 1,
  "config": {
    "population_size": 16,
    "num_genes": 4,
    "random_seed": 42
  },
  "data": {
    "population": [
      {
        "index": 0,
        "composition": {
          "op": "union",
          "children": [
            {
              "primitive": {
                "kind": "disk",
                "transform": {
                  "sx": 1.0037767936190125,
                  "sy": 0.7245823026467969,
                  "theta": 2.090278753489614,
                  "dx": 0.6408483264071972,
                  "dy": -0.6004267475774686
                },
                "color_rgb": [
                  0.8322598013952011,
                  0.8047643574968019,
                  0.38747837903017446
                ],
                "polygon_vertices": null
              }
            },
            {
              "primitive": {
                "kind": "polygon",
                "transform": {
                  "sx": 0.9579972789464778,
                  "sy": 1.1097052881024485,
                  "theta": -0.9140402996225859,
                  "dx": 1.5062336780636905,
                  "dy": 1.2579875882310327
                },
                "color_rgb": [
                  0.7783834970737619,
                  0.19463870785196757,
                  0.4667210037270342
                ],
                "polygon_vertices": [
                  [
                    0.3520650309986223,
                    0.5131056563818364
                  ],
                  [
                    -0.31264640316988396,
                    0.6058157917736708
                  ],
                  [
                    -0.20977179228210918,
                    -0.46889852852400543
                  ],
                  [
                    -0.01572675568165049,
                    -0.4776940933633832
                  ],
                  [
                    0.6711902915690842,
                    -0.13895402388084854
                  ]
                ]
              }
            },
            {
              "primitive": {
                "kind": "square",
                "transform": {
                  "sx": 0.6449576290790975,
                  "sy": 1.3121179866183221,
                  "theta": 0.9039312087064583,
                  "dx": 1.032837162466656,
                  "dy": -0.18107456375254039
                },
                "color_rgb": [
                  0.2272387217847769,
                  0.5545847870158348,
                  0.06381725610417532
                ],
                "polygon_vertices": null
              }
            },
            {
              "primitive": {
                "kind": "square",
                "transform": {
                  "sx": 0.7266541277024627,
                  "sy": 1.230317503893659,
                  "theta": 1.2400999002927888,
                  "dx": -1.2986324867595216,
                  "dy": 1.521991525237619
                },
                "color_rgb": [
                  0.761139701990353,
                  0.7860643052769538,
                  0.12811363267554587
                ],
                "polygon_vertices": null
              }
            }
          ]
        }
      },
      {
        "index": 1,
        "composition": {
          "op": "difference",
          "children": [
            {
              "op": "union",
              "children": [
                {
                  "primitive": {
                    "kind": "disk",
                    "transform": {
                      "sx": 0.34850456438041355,
                      "sy": 1.313075061207809,
                      "theta": -0.6435351876939284,
                      "dx": -0.6369641863009928,
                      "dy": -0.03653105487509336
                    },
                    "color_rgb": [
                      0.6628642127635824,
                      0.9556232570469699,
                      0.286446226882055
                    ],
                    "polygon_vertices": null
                  }
                },
                {
                  "primitive": {
                    "kind": "square",
                    "transform": {
                      "sx": 0.3461990055542374,
                      "sy": 0.8075959179447596,
                      "theta": 1.2205868813683043,
                      "dx": 0.25957314950688753,
                      "dy": -0.9607179146878156
                    },
                    "color_rgb": [
                      0.8041245261822627,
                      0.7154071296158017,
                      0.7389840039155418
                    ],
                    "polygon_vertices": null
                  }
                },
                {
                  "primitive": {
                    "kind": "disk",
                    "transform": {
                      "sx": 0.5723884074801138,
                      "sy": 1.1328858058894131,
                      "theta": 2.9645728677653254,
                      "dx": 0.002371795847495406,
                      "dy": -1.1395279918359975
                    },
                    "color_rgb": [
                      0.013936287708201545,
                      0.22965602999885526,
                      0.13182221778652103
                    ],
                    "polygon_vertices": null
                  }
                }
              ]
            },
            {
              "primitive": {
                "kind": "polygon",
                "transform": {
                  "sx": 0.22983138966350758,
                  "sy": 0.8662376507921896,
                  "theta": 0.8417904532423381,
                  "dx": -1.2611283079975895,
                  "dy": -1.1509132893954797
                },
                "color_rgb": [
                  0.41911431931630383,
                  0.9662319121431817,
                  0.5960425532343728
                ],
                "polygon_vertices": [
                  [
                    0.8725815749583844,
                    0.09820329652378743
                  ],
                  [
                    0.41760081635554297,
                    0.34170298748948874
                  ],
                  [
                    -0.7034255584947138,
                    0.14621824829217786
                  ],
                  [
                    0.1654684526316123,
                    -0.7454660609965016
                  ],
                  [
                    0.30837603987880535,
                    -0.8674609137737872
                  ],
                  [
                    0.36463170355632046,
                    -0.6689401496757056
                  ],
                  [
                    0.5910455981841589,
                    -0.26453158986547765
                  ]
                ]
              }
            }
          ]
        }
      },
      {
        "index": 2,
        "composition": {
          "op": "union",
          "children": [
            {
              "op": "union",
              "children": [
                {
                  "op": "difference",
                  "children": [
                    {
                      "primitive": {
                        "kind": "disk",
                        "transform": {
                          "sx": 0.4177980915158289,
                          "sy": 0.4840938453252752,
                          "theta": -1.574644301327705,
                          "dx": 0.2279444855768727,
                          "dy": -0.2679602377497847
                        },
                        "color_rgb": [
                          0.04925411992759399,
                          0.3736141384595716,
                          0.5237529487176372
                        ],
                        "polygon_vertices": null
                      }
                    },
                    {
                      "primitive": {
                        "kind": "disk",
                        "transform": {
                          "sx": 0.4839948355970974,
                          "sy": 1.0952171362921357,
                          "theta": 1.989060203057124,
                          "dx": -1.2631101444668003,
                          "dy": -1.38701165774343
                        },
                        "color_rgb": [
                          0.5944336637564518,
                          0.14617324419269828,
                          0.8246641904563413
                        ],
                        "polygon_vertices": null
                      }
                    }
                  ]
                },
                {
                  "primitive": {
                    "kind": "disk",
                    "transform": {
                      "sx": 0.3726463195653712,
                      "sy": 1.3051645669849403,
                      "theta": -2.1015261654273685,
                      "dx": -0.6888957365186062,
                      "dy": -1.1084371353854123
                    },
                    "color_rgb": [
                      0.11549006366535497,
                      0.021148016336440034,
                      0.05539540916426011
                    ],
                    "polygon_vertices": null
                  }
                }
              ]
            },
            {
              "primitive": {
                "kind": "disk",
                "transform": {
                  "sx": 0.26405831915261047,
                  "sy": 0.9093725793331654,
                  "theta": 1.13546285958057,
                  "dx": -0.3403825381375096,
                  "dy": -0.5824284897534419
                },
                "color_rgb": [
                  0.5045262370222301,
                  0.8750049422346086,
                  0.851131626822206
                ],
                "polygon_vertices": null
              }
            }
          ]
        }
      },
      {
        "index": 3,
        "composition": {
          "op": "union",
          "children": [
            {
              "op": "difference",
              "children": [
                {
                  "primitive": {
                    "kind": "square",
                    "transform": {
                      "sx": 0.7266541277024627,
                      "sy": 1.230317503893659,
                      "theta": 1.2400999002927888,
                      "dx": -1.2986324867595216,
                      "dy": 1.521991525237619
                    },
                    "color_rgb": [
                      0.761139701990353,
                      0.7860643052769538,
                      0.12811363267554587
                    ],
                    "polygon_vertices": null
                  }
                },
                {
                  "primitive": {
                    "kind": "polygon",
                    "transform": {
                      "sx": 0.22983138966350758,
                      "sy": 0.8662376507921896,
                      "theta": 0.8417904532423381,
                      "dx": -1.2611283079975895,
                      "dy": -1.1509132893954797
                    },
                    "color_rgb": [
                      0.41911431931630383,
                      0.9662319121431817,
                      0.5960425532343728
                    ],
                    "polygon_vertices": [
                      [
                        0.8725815749583844,
                        0.09820329652378743
                      ],
                      [
                        0.41760081635554297,
                        0.34170298748948874
                      ],
                      [
                        -0.7034255584947138,
                        0.14621824829217786
                      ],
                      [
                        0.1654684526316123,
                        -0.7454660609965016
                      ],
                      [
                        0.30837603987880535,
                        -0.8674609137737872
                      ],
                      [
                        0.36463170355632046,
                        -0.6689401496757056
                      ],
                      [
                        0.5910455981841589,
                        -0.26453158986547765
                      ]
                    ]
                  }
                }
              ]
            },
            {
              "primitive": {
                "kind": "square",
                "transform": {
                  "sx": 1.277708561349019,
                  "sy": 0.23757451104786126,
                  "theta": 2.790584873430433,
                  "dx": -0.050430551615103375,
                  "dy": 0.4419603893122791
                },
                "color_rgb": [
                  0.9930116413586993,
                  0.3059168827542868,
                  0.6851752500561108
                ],
                "polygon_vertices": null
              }
            }
          ]
        }
      },
      {
        "index": 4,
        "composition": {
          "op": "union",
          "children": [
            {
              "op": "union",
              "children": [
                {
                  "primitive": {
                    "kind": "disk",
                    "transform": {
                      "sx": 0.3817042088290338,
                      "sy": 1.1097667494597707,
                      "theta": -2.0022783393026584,
                      "dx": -0.6584761449839394,
                      "dy": -1.2724578409547098
                    },
                    "color_rgb": [
                      0.11037035248369528,
                      0.013175059950759186,
                      0.23515152582872412
                    ],
                    "polygon_vertices": null
                  }
                },
                {
                  "primitive": {
                    "kind": "disk",
                    "transform": {
                      "sx": 0.342209221846039,
                      "sy": 1.1428004873766973,
                      "theta": -2.090473070901319,
                      "dx": -0.6871789206548864,
                      "dy": -1.0711190389152498
                    },
                    "color_rgb": [
                      0.10038487590466204,
                      0.0,
                      0.0
                    ],
                    "polygon_vertices": null
                  }
                }
              ]
            },
            {
              "primitive": {
                "kind": "disk",
                "transform": {
                  "sx": 0.413413527037599,
                  "sy": 1.0682561401676136,
                  "theta": 1.1047917002067882,
                  "dx": -0.2816928391475244,
                  "dy": -0.8504346164586536
                },
                "color_rgb": [
                  0.607109921310754,
                  0.8788962629247545,
                  0.7666270940252908
                ],
                "polygon_vertices": null
              }
            }
          ]
        }
      },
      {
        "index": 5,
        "composition": {
          "op": "union",
          "children": [
            {
              "primitive": {
                "kind": "disk",
                "transform": {
                  "sx": 1.0037767936190125,
                  "sy": 0.7245823026467969,
                  "theta": 2.090278753489614,
                  "dx": 0.6408483264071972,
                  "dy": -0.6004267475774686
                },
                "color_rgb": [
                  0.8322598013952011,
                  0.8047643574968019,
                  0.38747837903017446
                ],
                "polygon_vertices": null
              }
            },
            {
              "primitive": {
                "kind": "disk",
                "transform": {
                  "sx": 0.34850456438041355,
                  "sy": 1.313075061207809,
                  "theta": -0.6435351876939284,
                  "dx": -0.6369641863009928,
                  "dy": -0.03653105487509336
                },
                "color_rgb": [
                  0.6628642127635824,
                  0.9556232570469699,
                  0.286446226882055
                ],
                "polygon_vertices": null
              }
            },
            {
              "primitive": {
                "kind": "square",
                "transform": {
                  "sx": 0.6828903513245823,
                  "sy": 1.2365243254067306,
                  "theta": 0.7594576816870444,
                  "dx": 1.0654218416882346,
                  "dy": -0.211387050560951
                },
                "color_rgb": [
                  0.16443211341223948,
                  0.5857300704461788,
                  0.023617998091254838
                ],
                "polygon_vertices": null
              }
            },
            {
              "primitive": {
                "kind": "square",
                "transform": {
                  "sx": 0.7266541277024627,
                  "sy": 1.230317503893659,
                  "theta": 1.2400999002927888,
                  "dx": -1.2986324867595216,
                  "dy": 1.521991525237619
                },
                "color_rgb": [
                  0.761139701990353,
                  0.7860643052769538,
                  0.12811363267554587
                ],
                "polygon_vertices": null
              }
            }
          ]
        }
      },
      {
        "index": 6,
        "composition": {
          "op": "difference",
          "children": [
            {
              "op": "union",
              "children": [
                {
                  "primitive": {
                    "kind": "square",
                    "transform": {
                      "sx": 0.7266541277024627,
                      "sy": 1.230317503893659,
                      "theta": 1.2400999002927888,
                      "dx": -1.2986324867595216,
                      "dy": 1.521991525237619
                    },
                    "color_rgb": [
                      0.761139701990353,
                      0.7860643052769538,
                      0.12811363267554587
                    ],
                    "polygon_vertices": null
                  }
                },
                {
                  "primitive": {
                    "kind": "square",
                    "transform": {
                      "sx": 0.24010932606151786,
                      "sy": 0.9529455984861382,
                      "theta": 1.4334082750795014,
                      "dx": 0.3143943204033127,
                      "dy": -0.48388986278268536
                    },
                    "color_rgb": [
                      0.7679412724738286,
                      0.6664321113256807,
                      0.8298441399047529
                    ],
                    "polygon_vertices": null
                  }
                },
                {
                  "primitive": {
                    "kind": "disk",
                    "transform": {
                      "sx": 0.6361332920955362,
                      "sy": 0.8423407659836009,
                      "theta": 3.048718649416684,
                      "dx": 0.044158183024266315,
                      "dy": -1.1374302085562036
                    },
                    "color_rgb": [
                      0.0805935545691549,
                      0.1314540880158252,
                      0.0
                    ],
                    "polygon_vertices": null
                  }
                },
                {
                  "primitive": {
                    "kind": "polygon",
                    "transform": {
                      "sx": 1.2950992929703173,
                      "sy": 0.4545768890279617,
                      "theta": -0.18974661570979462,
                      "dx": 0.7471836946010555,
                      "dy": 1.2107703481945653
                    },
                    "color_rgb": [
                      0.3790526950373052,
                      0.5170194868494292,
                      0.7417164105197349
                    ],
                    "polygon_vertices": [
                      [
                        0.3640867635059565,
                        0.2810069800574208
                      ],
                      [
                        -0.47298987442770923,
                        -0.22233195228999642
                      ],
                      [
                        0.1739853129541363,
                        -0.8280798434955944
                      ],
                      [
                        0.12318269804407952,
                        -0.395127872129681
                      ],
                      [
                        0.6557290271884446,
                        -0.7384066529056239
                      ],
                      [
                        0.5157079734227498,
                        -0.3553596098184753
                      ]
                    ]
                  }
                }
              ]
            },
            {
              "primitive": {
                "kind": "polygon",
                "transform": {
                  "sx": 0.22983138966350758,
                  "sy": 0.8662376507921896,
                  "theta": 0.8417904532423381,
                  "dx": -1.2611283079975895,
                  "dy": -1.1509132893954797
                },
                "color_rgb": [
                  0.41911431931630383,
                  0.9662319121431817,
                  0.5960425532343728
                ],
                "polygon_vertices": [
                  [
                    0.8725815749583844,
                    0.09820329652378743
                  ],
                  [
                    0.41760081635554297,
                    0.34170298748948874
                  ],
                  [
                    -0.7034255584947138,
                    0.14621824829217786
                  ],
                  [
                    0.1654684526316123,
                    -0.7454660609965016
                  ],
                  [
                    0.30837603987880535,
                    -0.8674609137737872
                  ],
                  [
                    0.36463170355632046,
                    -0.6689401496757056
                  ],
                  [
                    0.5910455981841589,
                    -0.26453158986547765
                  ]
                ]
              }
            }
          ]
        }
      },
      {
        "index": 7,
        "composition": {
          "op": "union",
          "children": [
            {
              "primitive": {
                "kind": "disk",
                "transform": {
                  "sx": 0.3579549196306185,
                  "sy": 1.0292831232110224,
                  "theta": -0.46246451832987123,
                  "dx": -0.595134543603907,
                  "dy": -0.18771499731862507
                },
                "color_rgb": [
                  0.4670050687238793,
                  0.9543913277540388,
                  0.2643494951034196
                ],
                "polygon_vertices": null
              }
            },
            {
              "primitive": {
                "kind": "disk",
                "transform": {
                  "sx": 0.26405831915261047,
                  "sy": 0.9093725793331654,
                  "theta": 1.13546285958057,
                  "dx": -0.3403825381375096,
                  "dy": -0.5824284897534419
                },
                "color_rgb": [
                  0.5045262370222301,
                  0.8750049422346086,
                  0.851131626822206
                ],
                "polygon_vertices": null
              }
            }
          ]
        }
      },
      {
        "index": 8,
        "composition": {
          "op": "union",
          "children": [
            {
              "primitive": {
                "kind": "disk",
                "transform": {
                  "sx": 0.6285218169950644,
                  "sy": 0.4689833732552406,
                  "theta": 1.9824438939297364,
                  "dx": 0.6841858264825033,
                  "dy": -0.4136846407805018
                },
                "color_rgb": [
                  0.7489561291156,
                  0.7489914687472804,
                  0.3466395163047018
                ],
                "polygon_vertices": null
              }
            },
            {
              "primitive": {
                "kind": "polygon",
                "transform": {
                  "sx": 0.8286495850251463,
                  "sy": 1.1815366188805176,
                  "theta": -1.0830446260429278,
                  "dx": 1.4594717284403234,
                  "dy": 1.4153885298125437
                },
                "color_rgb": [
                  0.6248192900811499,
                  0.2336078783839678,
                  0.47697632209966084
                ],
                "polygon_vertices": [
                  [
                    0.3520650309986223,
                    0.5131056563818364
                  ],
                  [
                    -0.31264640316988396,
                    0.6058157917736708
                  ],
                  [
                    -0.20977179228210918,
                    -0.46889852852400543
                  ],
                  [
                    -0.01572675568165049,
                    -0.4776940933633832
                  ],
                  [
                    0.6711902915690842,
                    -0.13895402388084854
                  ]
                ]
              }
            },
            {
              "primitive": {
                "kind": "square",
                "transform": {
                  "sx": 0.6449576290790975,
                  "sy": 1.3121179866183221,
                  "theta": 0.9039312087064583,
                  "dx": 1.032837162466656,
                  "dy": -0.18107456375254039
                },
                "color_rgb": [
                  0.2272387217847769,
                  0.5545847870158348,
                  0.06381725610417532
                ],
                "polygon_vertices": null
              }
            },
            {
              "primitive": {
                "kind": "square",
                "transform": {
                  "sx": 0.45340516233356326,
                  "sy": 1.3226059237675458,
                  "theta": 0.8475733463994333,
                  "dx": 0.9395060456724482,
                  "dy": 0.12797016182607135
                },
                "color_rgb": [
                  0.11961420175290007,
                  0.4794092022344848,
                  0.10352058610572444
                ],
                "polygon_vertices": null
              }
            }
          ]
        }
      },
      {
        "index": 9,
        "composition": {
          "op": "union",
          "children": [
            {
              "op": "union",
              "children": [
                {
                  "op": "difference",
                  "children": [
                    {
                      "op": "union",
                      "children": [
                        {
                          "primitive": {
                            "kind": "disk",
                            "transform": {
                              "sx": 0.9560908113247432,
                              "sy": 0.594531514198283,
                              "theta": 1.6200791464960993,
                              "dx": 0.7202603374760556,
                              "dy": -0.39591244076461385
                            },
                            "color_rgb": [
                              0.8441823875079403,
                              0.7476194355771282,
                              0.37086259483520123
                            ],
                            "polygon_vertices": null
                          }
                        },
                        {
                          "primitive": {
                            "kind": "polygon",
                            "transform": {
                              "sx": 0.9693542721400028,
                              "sy": 1.1106077901678593,
                              "theta": -0.9721076321036448,
                              "dx": 1.4807757086006337,
                              "dy": 1.3200564358095648
                            },
                            "color_rgb": [
                              0.8232159036710778,
                              0.3111694614066853,
                              0.6314604034873671
                            ],
                            "polygon_vertices": [
                              [
                                0.3520650309986223,
                                0.5131056563818364
                              ],
                              [
                                -0.31264640316988396,
                                0.6058157917736708
                              ],
                              [
                                -0.20977179228210918,
                                -0.46889852852400543
                              ],
                              [
                                -0.01572675568165049,
                                -0.4776940933633832
                              ],
                              [
                                0.6711902915690842,
                                -0.13895402388084854
                              ]
                            ]
                          }
                        },
                        {
                          "primitive": {
                            "kind": "square",
                            "transform": {
                              "sx": 0.7860010488116358,
                              "sy": 1.442013282380895,
                              "theta": 0.8819620231025533,
                              "dx": 1.1212691953719962,
                              "dy": -0.3537042401303754
                            },
                            "color_rgb": [
                              0.24839969506428192,
                              0.6432241829726301,
                              0.11289392700355722
                            ],
                            "polygon_vertices": null
                          }
                        },
                        {
                          "primitive": {
                            "kind": "square",
                            "transform": {
                              "sx": 0.2870649713245464,
                              "sy": 1.2877503643514163,
                              "theta": 1.3240602145260443,
                              "dx": -1.255228613215955,
                              "dy": 1.4686367779019638
                            },
                            "color_rgb": [
                              0.39629841946887456,
                              0.613717964536412,
                              0.17329049276964428
                            ],
                            "polygon_vertices": null
                          }
                        }
                      ]
                    },
                    {
                      "primitive": {
                        "kind": "disk",
                        "transform": {
                          "sx": 0.4839948355970974,
                          "sy": 1.0952171362921357,
                          "theta": 1.989060203057124,
                          "dx": -1.2631101444668003,
                          "dy": -1.38701165774343
                        },
                        "color_rgb": [
                          0.5944336637564518,
                          0.14617324419269828,
                          0.8246641904563413
                        ],
                        "polygon_vertices": null
                      }
                    }
                  ]
                },
                {
                  "primitive": {
                    "kind": "disk",
                    "transform": {
                      "sx": 0.709084366425819,
                      "sy": 1.3048765890084884,
                      "theta": -2.2225336983205377,
                      "dx": -0.795711042800447,
                      "dy": -0.9028559870932925
                    },
                    "color_rgb": [
                      0.15629368135348165,
                      0.18283545618630082,
                      0.06849812078360207
                    ],
                    "polygon_vertices": null
                  }
                }
              ]
            },
            {
              "primitive": {
                "kind": "disk",
                "transform": {
                  "sx": 0.22568350845148696,
                  "sy": 0.7980437652335499,
                  "theta": 0.7942774465301787,
                  "dx": -0.3568416558916531,
                  "dy": -0.5877701001819555
                },
                "color_rgb": [
                  0.5969620127409735,
                  0.8784661296531341,
                  0.822852051907449
                ],
                "polygon_vertices": null
              }
            }
          ]
        }
      },
      {
        "index": 10,
        "composition": {
          "op": "union",
          "children": [
            {
              "primitive": {
                "kind": "disk",
                "transform": {
                  "sx": 1.0732822645239155,
                  "sy": 0.4949750140582909,
                  "theta": 2.20123193083539,
                  "dx": 0.5789977955764877,
                  "dy": -0.8129530614669997
                },
                "color_rgb": [
                  0.8552079729415617,
                  0.8783226667396392,
                  0.42491702420080074
                ],
                "polygon_vertices": null
              }
            },
            {
              "primitive": {
                "kind": "polygon",
                "transform": {
                  "sx": 0.8855787551377811,
                  "sy": 1.2402886295154074,
                  "theta": -0.9896952394901977,
                  "dx": 1.295593313350078,
                  "dy": 1.3076436114804622
                },
                "color_rgb": [
                  0.9263109481411849,
                  0.3740757133120035,
                  0.5982017908776247
                ],
                "polygon_vertices": [
                  [
                    0.3520650309986223,
                    0.5131056563818364
                  ],
                  [
                    -0.31264640316988396,
                    0.6058157917736708
                  ],
                  [
                    -0.20977179228210918,
                    -0.46889852852400543
                  ],
                  [
                    -0.01572675568165049,
                    -0.4776940933633832
                  ],
                  [
                    0.6711902915690842,
                    -0.13895402388084854
                  ]
                ]
              }
            },
            {
              "primitive": {
                "kind": "disk",
                "transform": {
                  "sx": 0.43741271970256057,
                  "sy": 0.6076568151067026,
                  "theta": -1.5443498140028395,
                  "dx": 0.2808525100308241,
                  "dy": -0.15293680698214818
                },
                "color_rgb": [
                  0.043325855325000766,
                  0.30068544482220544,
                  0.48230564213405136
                ],
                "polygon_vertices": null
              }
            },
            {
              "primitive": {
                "kind": "square",
                "transform": {
                  "sx": 0.6704279082678213,
                  "sy": 1.3437547284381297,
                  "theta": 1.4076197108433366,
                  "dx": -1.2981834930795282,
                  "dy": 1.5730230217678698
                },
                "color_rgb": [
                  0.7990239623361924,
                  0.6625829965858059,
                  0.2723441117941703
                ],
                "polygon_vertices": null
              }
            }
          ]
        }
      },
      {
        "index": 11,
        "composition": {
          "op": "difference",
          "children": [
            {
              "op": "union",
              "children": [
                {
                  "primitive": {
                    "kind": "disk",
                    "transform": {
                      "sx": 0.3959117449770565,
                      "sy": 1.374549329807113,
                      "theta": -0.5585663473957525,
                      "dx": -0.6874889814470817,
                      "dy": 0.05642423994727847
                    },
                    "color_rgb": [
                      0.7244776795638063,
                      0.7448279228692256,
                      0.2500024016556089
                    ],
                    "polygon_vertices": null
                  }
                },
                {
                  "primitive": {
                    "kind": "square",
                    "transform": {
                      "sx": 0.3461990055542374,
                      "sy": 0.8075959179447596,
                      "theta": 1.2205868813683043,
                      "dx": 0.25957314950688753,
                      "dy": -0.9607179146878156
                    },
                    "color_rgb": [
                      0.8041245261822627,
                      0.7154071296158017,
                      0.7389840039155418
                    ],
                    "polygon_vertices": null
                  }
                },
                {
                  "primitive": {
                    "kind": "square",
                    "transform": {
                      "sx": 0.7570703849403179,
                      "sy": 1.1552633422841239,
                      "theta": 1.5370084984730692,
                      "dx": -1.2993274325931734,
                      "dy": 1.6788213664560712
                    },
                    "color_rgb": [
                      0.8096558132449267,
                      0.7332725415445225,
                      0.127974367531211
                    ],
                    "polygon_vertices": null
                  }
                }
              ]
            },
            {
              "primitive": {
                "kind": "polygon",
                "transform": {
                  "sx": 0.22983138966350758,
                  "sy": 0.8662376507921896,
                  "theta": 0.8417904532423381,
                  "dx": -1.2611283079975895,
                  "dy": -1.1509132893954797
                },
                "color_rgb": [
                  0.41911431931630383,
                  0.9662319121431817,
                  0.5960425532343728
                ],
                "polygon_vertices": [
                  [
                    0.8725815749583844,
                    0.09820329652378743
                  ],
                  [
                    0.41760081635554297,
                    0.34170298748948874
                  ],
                  [
                    -0.7034255584947138,
                    0.14621824829217786
                  ],
                  [
                    0.1654684526316123,
                    -0.7454660609965016
                  ],
                  [
                    0.30837603987880535,
                    -0.8674609137737872
                  ],
                  [
                    0.36463170355632046,
                    -0.6689401496757056
                  ],
                  [
                    0.5910455981841589,
                    -0.26453158986547765
                  ]
                ]
              }
            }
          ]
        }
      },
      {
        "index": 12,
        "composition": {
          "op": "union",
          "children": [
            {
              "op": "union",
              "children": [
                {
                  "op": "difference",
                  "children": [
                    {
                      "op": "union",
                      "children": [
                        {
                          "primitive": {
                            "kind": "disk",
                            "transform": {
                              "sx": 0.26785517784496016,
                              "sy": 1.394464230701603,
                              "theta": -0.8583366923378208,
                              "dx": -0.6216753031950942,
                              "dy": -0.1508795735792412
                            },
                            "color_rgb": [
                              0.5673016960234426,
                              0.999374481908957,
                              0.16227067399421574
                            ],
                            "polygon_vertices": null
                          }
                        },
                        {
                          "primitive": {
                            "kind": "square",
                            "transform": {
                              "sx": 0.3461990055542374,
                              "sy": 0.8075959179447596,
                              "theta": 1.2205868813683043,
                              "dx": 0.25957314950688753,
                              "dy": -0.9607179146878156
                            },
                            "color_rgb": [
                              0.8041245261822627,
                              0.7154071296158017,
                              0.7389840039155418
                            ],
                            "polygon_vertices": null
                          }
                        },
                        {
                          "primitive": {
                            "kind": "disk",
                            "transform": {
                              "sx": 0.5723884074801138,
                              "sy": 1.1328858058894131,
                              "theta": 2.9645728677653254,
                              "dx": 0.002371795847495406,
                              "dy": -1.1395279918359975
                            },
                            "color_rgb": [
                              0.013936287708201545,
                              0.22965602999885526,
                              0.13182221778652103
                            ],
                            "polygon_vertices": null
                          }
                        }
                      ]
                    },
                    {
                      "primitive": {
                        "kind": "disk",
                        "transform": {
                          "sx": 0.5456706232994919,
                          "sy": 1.1129693233003664,
                          "theta": 2.026520806553944,
                          "dx": -1.4697074927948552,
                          "dy": -1.16620947276991
                        },
                        "color_rgb": [
                          0.6389063455759751,
                          0.1308047337564965,
                          0.9700692086020871
                        ],
                        "polygon_vertices": null
                      }
                    }
                  ]
                },
                {
                  "primitive": {
                    "kind": "disk",
                    "transform": {
                      "sx": 0.3726463195653712,
                      "sy": 1.3051645669849403,
                      "theta": -2.1015261654273685,
                      "dx": -0.6888957365186062,
                      "dy": -1.1084371353854123
                    },
                    "color_rgb": [
                      0.11549006366535497,
                      0.021148016336440034,
                      0.05539540916426011
                    ],
                    "polygon_vertices": null
                  }
                }
              ]
            },
            {
              "primitive": {
                "kind": "disk",
                "transform": {
                  "sx": 0.26405831915261047,
                  "sy": 0.9093725793331654,
                  "theta": 1.13546285958057,
                  "dx": -0.3403825381375096,
                  "dy": -0.5824284897534419
                },
                "color_rgb": [
                  0.5045262370222301,
                  0.8750049422346086,
                  0.851131626822206
                ],
                "polygon_vertices": null
              }
            }
          ]
        }
      },
      {
        "index": 13,
        "composition": {
          "op": "union",
          "children": [
            {
              "primitive": {
                "kind": "disk",
                "transform": {
                  "sx": 0.10958542542218441,
                  "sy": 1.176143363199985,
                  "theta": -0.7008583510820054,
                  "dx": -0.6664970411065793,
                  "dy": -0.2037235993352824
                },
                "color_rgb": [
                  0.685542817374496,
                  1.0,
                  0.5673673130050053
                ],
                "polygon_vertices": null
              }
            },
            {
              "primitive": {
                "kind": "disk",
                "transform": {
                  "sx": 0.26405831915261047,
                  "sy": 0.9093725793331654,
                  "theta": 1.13546285958057,
                  "dx": -0.3403825381375096,
                  "dy": -0.5824284897534419
                },
                "color_rgb": [
                  0.5045262370222301,
                  0.8750049422346086,
                  0.851131626822206
                ],
                "polygon_vertices": null
              }
            }
          ]
        }
      },
      {
        "index": 14,
        "composition": {
          "op": "intersection",
          "children": [
            {
              "primitive": {
                "kind": "disk",
                "transform": {
                  "sx": 1.0037767936190125,
                  "sy": 0.7245823026467969,
                  "theta": 2.090278753489614,
                  "dx": 0.6408483264071972,
                  "dy": -0.6004267475774686
                },
                "color_rgb": [
                  0.8322598013952011,
                  0.8047643574968019,
                  0.38747837903017446
                ],
                "polygon_vertices": null
              }
            },
            {
              "primitive": {
                "kind": "polygon",
                "transform": {
                  "sx": 0.9579972789464778,
                  "sy": 1.1097052881024485,
                  "theta": -0.9140402996225859,
                  "dx": 1.5062336780636905,
                  "dy": 1.2579875882310327
                },
                "color_rgb": [
                  0.7783834970737619,
                  0.19463870785196757,
                  0.4667210037270342
                ],
                "polygon_vertices": [
                  [
                    0.3520650309986223,
                    0.5131056563818364
                  ],
                  [
                    -0.31264640316988396,
                    0.6058157917736708
                  ],
                  [
                    -0.20977179228210918,
                    -0.46889852852400543
                  ],
                  [
                    -0.01572675568165049,
                    -0.4776940933633832
                  ],
                  [
                    0.6711902915690842,
                    -0.13895402388084854
                  ]
                ]
              }
            },
            {
              "primitive": {
                "kind": "square",
                "transform": {
                  "sx": 0.5555442941306725,
                  "sy": 1.3133938306267952,
                  "theta": 0.8347561861850297,
                  "dx": 0.8012933820883437,
                  "dy": -0.08308783126035633
                },
                "color_rgb": [
                  0.30673194707633966,
                  0.5726211813184746,
                  0.0
                ],
                "polygon_vertices": null
              }
            },
            {
              "primitive": {
                "kind": "square",
                "transform": {
                  "sx": 0.6449576290790975,
                  "sy": 1.3121179866183221,
                  "theta": 0.9039312087064583,
                  "dx": 1.032837162466656,
                  "dy": -0.18107456375254039
                },
                "color_rgb": [
                  0.2272387217847769,
                  0.5545847870158348,
                  0.06381725610417532
                ],
                "polygon_vertices": null
              }
            }
          ]
        }
      },
      {
        "index": 15,
        "composition": {
          "op": "difference",
          "children": [
            {
              "op": "union",
              "children": [
                {
                  "primitive": {
                    "kind": "disk",
                    "transform": {
                      "sx": 0.18390391319835703,
                      "sy": 1.4181835347367469,
                      "theta": -0.5136200443573027,
                      "dx": -0.5448493097340993,
                      "dy": 0.05322100218613906
                    },
                    "color_rgb": [
                      0.527282815650927,
                      0.8761633115344645,
                      0.4168027336628638
                    ],
                    "polygon_vertices": null
                  }
                },
                {
                  "primitive": {
                    "kind": "square",
                    "transform": {
                      "sx": 0.310133425993686,
                      "sy": 0.8229006125308457,
                      "theta": 0.9325246710491122,
                      "dx": 0.48268289295976696,
                      "dy": -1.0014690722409094
                    },
                    "color_rgb": [
                      0.8120233978162636,
                      0.8287751774914718,
                      0.7028569614151972
                    ],
                    "polygon_vertices": null
                  }
                },
                {
                  "primitive": {
                    "kind": "disk",
                    "transform": {
                      "sx": 0.45991640673743617,
                      "sy": 1.0975114015631853,
                      "theta": 2.965350005311734,
                      "dx": -0.1459222765676955,
                      "dy": -1.0719804001294255
                    },
                    "color_rgb": [
                      0.0,
                      0.20264051706514563,
                      0.30895634201328936
                    ],
                    "polygon_vertices": null
                  }
                }
              ]
            },
            {
              "primitive": {
                "kind": "polygon",
                "transform": {
                  "sx": 0.19037037599505466,
                  "sy": 0.7633597493656932,
                  "theta": 0.6182386152474688,
                  "dx": -1.2977127245241902,
                  "dy": -1.4655309330370008
                },
                "color_rgb": [
                  0.5572850786540835,
                  0.9497381346035598,
                  0.7248869781661981
                ],
                "polygon_vertices": [
                  [
                    0.8725815749583844,
                    0.09820329652378743
                  ],
                  [
                    0.41760081635554297,
                    0.34170298748948874
                  ],
                  [
                    -0.7034255584947138,
                    0.14621824829217786
                  ],
                  [
                    0.1654684526316123,
                    -0.7454660609965016
                  ],
                  [
                    0.30837603987880535,
                    -0.8674609137737872
                  ],
                  [
                    0.36463170355632046,
                    -0.6689401496757056
                  ],
                  [
                    0.5910455981841589,
                    -0.26453158986547765
                  ]
                ]
              }
            }
          ]
        }
      }
    ]
  }
}